symbolhkdf/__init__.py
symbolhkdf/crypto.py
symbolhkdf/pure_pynacl/__init__.py
symbolhkdf/pure_pynacl/tweetnacl.py
symbol_hkdf_python-0.2.4.dist-info/METADATA
symbol_hkdf_python-0.2.4.dist-info/WHEEL
symbol_hkdf_python-0.2.4.dist-info/top_level.txt
symbol_hkdf_python-0.2.4.dist-info/RECORD
