Metadata-Version: 2.1
Name: symbol-hkdf-python
Version: 0.2.4
Summary: encrypt and decrypt tool for symbol
Home-page: https://github.com/monakaJP/symbol-hkdf-python
Author: monakaJP
Author-email: notify.monakaxym@gmail.com
License: apache2.0
Keywords: https://github.com/monakaJP/symbol-hkdf-python
Platform: UNKNOWN
Classifier: Programming Language :: Python :: 3.6
Requires-Dist: cryptography (>=37.0.2)
